plaid_ops/__init__.py
plaid_ops/_version.py
plaid_ops/common/__init__.py
plaid_ops/common/visualization.py
plaid_ops/mesh/__init__.py
plaid_ops/mesh/feature_engineering.py
plaid_ops/mesh/transformations.py
plaid_ops-0.1.8.dist-info/licenses/LICENSE.txt
plaid_ops-0.1.8.dist-info/METADATA
plaid_ops-0.1.8.dist-info/WHEEL
plaid_ops-0.1.8.dist-info/top_level.txt
plaid_ops-0.1.8.dist-info/RECORD
